LMTodo/__init__.py
LMTodo/__main__.py
LMTodo/main.py
LMTodo/controllers/__init__.py
LMTodo/controllers/todo_controller.py
LMTodo/models/__init__.py
LMTodo/models/parser.py
LMTodo/models/qthread_helper.py
LMTodo/models/todo_db.py
LMTodo/views/__init__.py
LMTodo/views/lmtodo_icons.py
LMTodo/views/settings_panel.py
LMTodo/views/task_panel.py
LMTodo/views/translations.py
LMTodo/views/widgets.py
lmtodo-0.1.7.dist-info/licenses/LICENSE
lmtodo-0.1.7.dist-info/METADATA
lmtodo-0.1.7.dist-info/WHEEL
lmtodo-0.1.7.dist-info/entry_points.txt
lmtodo-0.1.7.dist-info/top_level.txt
lmtodo-0.1.7.dist-info/RECORD
